[
    {
        "name": "land",
        "type": "LOCATION",
        "metadata": [],
        "salience": 0.6235646,
        "mentions": [
            {
                "text": {
                    "content": "land",
                    "beginOffset": 7
                },
                "type": "COMMON"
            }
        ]
    },
    {
        "name": "inheritance",
        "type": "OTHER",
        "metadata": [],
        "salience": 0.16253708,
        "mentions": [
            {
                "text": {
                    "content": "inheritance",
                    "beginOffset": 44
                },
                "type": "COMMON"
            }
        ]
    },
    {
        "name": "number",
        "type": "OTHER",
        "metadata": [],
        "salience": 0.12488885,
        "mentions": [
            {
                "text": {
                    "content": "number",
                    "beginOffset": 69
                },
                "type": "COMMON"
            }
        ]
    },
    {
        "name": "names",
        "type": "OTHER",
        "metadata": [],
        "salience": 0.08900945,
        "mentions": [
            {
                "text": {
                    "content": "names",
                    "beginOffset": 79
                },
                "type": "COMMON"
            }
        ]
    }
]