[
    {
        "name": "son",
        "type": "PERSON",
        "metadata": [],
        "salience": 0.33511612,
        "mentions": [
            {
                "text": {
                    "content": "son",
                    "beginOffset": 15
                },
                "type": "COMMON"
            }
        ]
    },
    {
        "name": "message",
        "type": "OTHER",
        "metadata": [],
        "salience": 0.15702309,
        "mentions": [
            {
                "text": {
                    "content": "message",
                    "beginOffset": 158
                },
                "type": "COMMON"
            }
        ]
    },
    {
        "name": "people",
        "type": "PERSON",
        "metadata": [],
        "salience": 0.1414044,
        "mentions": [
            {
                "text": {
                    "content": "people",
                    "beginOffset": 32
                },
                "type": "COMMON"
            }
        ]
    },
    {
        "name": "man",
        "type": "PERSON",
        "metadata": [],
        "salience": 0.10226762,
        "mentions": [
            {
                "text": {
                    "content": "man",
                    "beginOffset": 22
                },
                "type": "COMMON"
            }
        ]
    },
    {
        "name": "walls",
        "type": "OTHER",
        "metadata": [],
        "salience": 0.070960514,
        "mentions": [
            {
                "text": {
                    "content": "walls",
                    "beginOffset": 77
                },
                "type": "COMMON"
            }
        ]
    },
    {
        "name": "doors",
        "type": "OTHER",
        "metadata": [],
        "salience": 0.070960514,
        "mentions": [
            {
                "text": {
                    "content": "doors",
                    "beginOffset": 94
                },
                "type": "COMMON"
            }
        ]
    },
    {
        "name": "houses",
        "type": "LOCATION",
        "metadata": [],
        "salience": 0.0652899,
        "mentions": [
            {
                "text": {
                    "content": "houses",
                    "beginOffset": 107
                },
                "type": "COMMON"
            }
        ]
    },
    {
        "name": "Lord",
        "type": "PERSON",
        "metadata": [],
        "salience": 0.034948807,
        "mentions": [
            {
                "text": {
                    "content": "Lord",
                    "beginOffset": 189
                },
                "type": "COMMON"
            }
        ]
    },
    {
        "name": "each other",
        "type": "PERSON",
        "metadata": [],
        "salience": 0.022029033,
        "mentions": [
            {
                "text": {
                    "content": "each other",
                    "beginOffset": 125
                },
                "type": "COMMON"
            }
        ]
    }
]