[
    {
        "name": "priest",
        "type": "PERSON",
        "metadata": [],
        "salience": 0.5433041,
        "mentions": [
            {
                "text": {
                    "content": "priest",
                    "beginOffset": 4
                },
                "type": "COMMON"
            }
        ]
    },
    {
        "name": "some",
        "type": "OTHER",
        "metadata": [],
        "salience": 0.25282976,
        "mentions": [
            {
                "text": {
                    "content": "some",
                    "beginOffset": 27
                },
                "type": "COMMON"
            }
        ]
    },
    {
        "name": "oil",
        "type": "OTHER",
        "metadata": [],
        "salience": 0.07276455,
        "mentions": [
            {
                "text": {
                    "content": "oil",
                    "beginOffset": 46
                },
                "type": "COMMON"
            }
        ]
    },
    {
        "name": "log",
        "type": "OTHER",
        "metadata": [],
        "salience": 0.07192368,
        "mentions": [
            {
                "text": {
                    "content": "log",
                    "beginOffset": 39
                },
                "type": "COMMON"
            }
        ]
    },
    {
        "name": "hand",
        "type": "OTHER",
        "metadata": [],
        "salience": 0.036241367,
        "mentions": [
            {
                "text": {
                    "content": "hand",
                    "beginOffset": 87
                },
                "type": "COMMON"
            }
        ]
    },
    {
        "name": "palm",
        "type": "OTHER",
        "metadata": [],
        "salience": 0.022936543,
        "mentions": [
            {
                "text": {
                    "content": "palm",
                    "beginOffset": 66
                },
                "type": "COMMON"
            }
        ]
    }
]