[
    {
        "name": "priest",
        "type": "PERSON",
        "metadata": [],
        "salience": 0.36235145,
        "mentions": [
            {
                "text": {
                    "content": "priest",
                    "beginOffset": 9
                },
                "type": "COMMON"
            }
        ]
    },
    {
        "name": "some",
        "type": "OTHER",
        "metadata": [],
        "salience": 0.27313682,
        "mentions": [
            {
                "text": {
                    "content": "some",
                    "beginOffset": 27
                },
                "type": "COMMON"
            }
        ]
    },
    {
        "name": "blood",
        "type": "OTHER",
        "metadata": [],
        "salience": 0.0724643,
        "mentions": [
            {
                "text": {
                    "content": "blood",
                    "beginOffset": 39
                },
                "type": "COMMON"
            }
        ]
    },
    {
        "name": "sin offering",
        "type": "OTHER",
        "metadata": [],
        "salience": 0.04973068,
        "mentions": [
            {
                "text": {
                    "content": "sin offering",
                    "beginOffset": 52
                },
                "type": "COMMON"
            }
        ]
    },
    {
        "name": "altar",
        "type": "OTHER",
        "metadata": [],
        "salience": 0.046309687,
        "mentions": [
            {
                "text": {
                    "content": "altar",
                    "beginOffset": 112
                },
                "type": "COMMON"
            }
        ]
    },
    {
        "name": "horns",
        "type": "OTHER",
        "metadata": [],
        "salience": 0.04439782,
        "mentions": [
            {
                "text": {
                    "content": "horns",
                    "beginOffset": 99
                },
                "type": "COMMON"
            }
        ]
    },
    {
        "name": "finger",
        "type": "OTHER",
        "metadata": [],
        "salience": 0.04387201,
        "mentions": [
            {
                "text": {
                    "content": "finger",
                    "beginOffset": 74
                },
                "type": "COMMON"
            }
        ]
    },
    {
        "name": "blood",
        "type": "OTHER",
        "metadata": [],
        "salience": 0.035183106,
        "mentions": [
            {
                "text": {
                    "content": "blood",
                    "beginOffset": 165
                },
                "type": "COMMON"
            }
        ]
    },
    {
        "name": "altar",
        "type": "OTHER",
        "metadata": [],
        "salience": 0.024809584,
        "mentions": [
            {
                "text": {
                    "content": "altar",
                    "beginOffset": 190
                },
                "type": "COMMON"
            }
        ]
    },
    {
        "name": "base",
        "type": "LOCATION",
        "metadata": [],
        "salience": 0.021837318,
        "mentions": [
            {
                "text": {
                    "content": "base",
                    "beginOffset": 178
                },
                "type": "COMMON"
            }
        ]
    },
    {
        "name": "burnt offering",
        "type": "OTHER",
        "metadata": [],
        "salience": 0.015643593,
        "mentions": [
            {
                "text": {
                    "content": "burnt offering",
                    "beginOffset": 121
                },
                "type": "COMMON"
            }
        ]
    },
    {
        "name": "rest",
        "type": "OTHER",
        "metadata": [],
        "salience": 0.010263641,
        "mentions": [
            {
                "text": {
                    "content": "rest",
                    "beginOffset": 153
                },
                "type": "COMMON"
            }
        ]
    }
]