[
    {
        "name": "Joseph",
        "type": "PERSON",
        "metadata": [],
        "salience": 0.52994233,
        "mentions": [
            {
                "text": {
                    "content": "Joseph",
                    "beginOffset": 0
                },
                "type": "PROPER"
            }
        ]
    },
    {
        "name": "brothers",
        "type": "PERSON",
        "metadata": [],
        "salience": 0.17474037,
        "mentions": [
            {
                "text": {
                    "content": "brothers",
                    "beginOffset": 40
                },
                "type": "COMMON"
            }
        ]
    },
    {
        "name": "father",
        "type": "PERSON",
        "metadata": [],
        "salience": 0.06853633,
        "mentions": [
            {
                "text": {
                    "content": "father",
                    "beginOffset": 25
                },
                "type": "COMMON"
            }
        ]
    },
    {
        "name": "father",
        "type": "PERSON",
        "metadata": [],
        "salience": 0.06165757,
        "mentions": [
            {
                "text": {
                    "content": "father",
                    "beginOffset": 61
                },
                "type": "COMMON"
            }
        ]
    },
    {
        "name": "household",
        "type": "OTHER",
        "metadata": [],
        "salience": 0.05009963,
        "mentions": [
            {
                "text": {
                    "content": "household",
                    "beginOffset": 72
                },
                "type": "COMMON"
            }
        ]
    },
    {
        "name": "food",
        "type": "OTHER",
        "metadata": [],
        "salience": 0.05009963,
        "mentions": [
            {
                "text": {
                    "content": "food",
                    "beginOffset": 87
                },
                "type": "COMMON"
            }
        ]
    },
    {
        "name": "number",
        "type": "OTHER",
        "metadata": [],
        "salience": 0.038071647,
        "mentions": [
            {
                "text": {
                    "content": "number",
                    "beginOffset": 110
                },
                "type": "COMMON"
            }
        ]
    },
    {
        "name": "children",
        "type": "PERSON",
        "metadata": [],
        "salience": 0.0268525,
        "mentions": [
            {
                "text": {
                    "content": "children",
                    "beginOffset": 126
                },
                "type": "COMMON"
            }
        ]
    }
]