[
    {
        "name": "God",
        "type": "PERSON",
        "metadata": {
            "wikipedia_url": "https:\/\/en.wikipedia.org\/wiki\/God",
            "mid": "\/m\/0d05l6"
        },
        "salience": 0.66014934,
        "mentions": [
            {
                "text": {
                    "content": "God",
                    "beginOffset": 4
                },
                "type": "PROPER"
            },
            {
                "text": {
                    "content": "God",
                    "beginOffset": 164
                },
                "type": "PROPER"
            }
        ]
    },
    {
        "name": "all",
        "type": "PERSON",
        "metadata": [],
        "salience": 0.10029404,
        "mentions": [
            {
                "text": {
                    "content": "all",
                    "beginOffset": 113
                },
                "type": "COMMON"
            }
        ]
    },
    {
        "name": "Jesus of Nazareth",
        "type": "PERSON",
        "metadata": {
            "mid": "\/m\/045m1_",
            "wikipedia_url": "https:\/\/en.wikipedia.org\/wiki\/Jesus"
        },
        "salience": 0.08438039,
        "mentions": [
            {
                "text": {
                    "content": "Jesus of Nazareth",
                    "beginOffset": 17
                },
                "type": "PROPER"
            }
        ]
    },
    {
        "name": "power",
        "type": "OTHER",
        "metadata": [],
        "salience": 0.0570428,
        "mentions": [
            {
                "text": {
                    "content": "power",
                    "beginOffset": 60
                },
                "type": "COMMON"
            }
        ]
    },
    {
        "name": "Holy Spirit",
        "type": "OTHER",
        "metadata": {
            "mid": "\/m\/03qsc",
            "wikipedia_url": "https:\/\/en.wikipedia.org\/wiki\/Holy_Spirit"
        },
        "salience": 0.044369463,
        "mentions": [
            {
                "text": {
                    "content": "Holy Spirit",
                    "beginOffset": 44
                },
                "type": "PROPER"
            }
        ]
    },
    {
        "name": "devil",
        "type": "OTHER",
        "metadata": [],
        "salience": 0.035693,
        "mentions": [
            {
                "text": {
                    "content": "devil",
                    "beginOffset": 149
                },
                "type": "COMMON"
            }
        ]
    },
    {
        "name": "power",
        "type": "OTHER",
        "metadata": [],
        "salience": 0.01807096,
        "mentions": [
            {
                "text": {
                    "content": "power",
                    "beginOffset": 136
                },
                "type": "COMMON"
            }
        ]
    }
]