[
    {
        "name": "minds",
        "type": "OTHER",
        "metadata": [],
        "salience": 0.32233915,
        "mentions": [
            {
                "text": {
                    "content": "minds",
                    "beginOffset": 79
                },
                "type": "COMMON"
            }
        ]
    },
    {
        "name": "cunning",
        "type": "OTHER",
        "metadata": [],
        "salience": 0.17564496,
        "mentions": [
            {
                "text": {
                    "content": "cunning",
                    "beginOffset": 65
                },
                "type": "COMMON"
            }
        ]
    },
    {
        "name": "serpent",
        "type": "OTHER",
        "metadata": [],
        "salience": 0.17360258,
        "mentions": [
            {
                "text": {
                    "content": "serpent",
                    "beginOffset": 53
                },
                "type": "COMMON"
            }
        ]
    },
    {
        "name": "Eve",
        "type": "PERSON",
        "metadata": {
            "mid": "\/m\/025t1rz",
            "wikipedia_url": "https:\/\/en.wikipedia.org\/wiki\/Eve"
        },
        "salience": 0.15304781,
        "mentions": [
            {
                "text": {
                    "content": "Eve",
                    "beginOffset": 29
                },
                "type": "PROPER"
            }
        ]
    },
    {
        "name": "devotion",
        "type": "OTHER",
        "metadata": [],
        "salience": 0.123314574,
        "mentions": [
            {
                "text": {
                    "content": "devotion",
                    "beginOffset": 138
                },
                "type": "COMMON"
            }
        ]
    },
    {
        "name": "Christ",
        "type": "PERSON",
        "metadata": {
            "wikipedia_url": "https:\/\/en.wikipedia.org\/wiki\/Jesus",
            "mid": "\/m\/045m1_"
        },
        "salience": 0.05205093,
        "mentions": [
            {
                "text": {
                    "content": "Christ",
                    "beginOffset": 150
                },
                "type": "PROPER"
            }
        ]
    }
]