[
    {
        "name": "shoot",
        "type": "EVENT",
        "metadata": [],
        "salience": 0.46111107,
        "mentions": [
            {
                "text": {
                    "content": "shoot",
                    "beginOffset": 2
                },
                "type": "COMMON"
            }
        ]
    },
    {
        "name": "Jesse",
        "type": "PERSON",
        "metadata": [],
        "salience": 0.29595053,
        "mentions": [
            {
                "text": {
                    "content": "Jesse",
                    "beginOffset": 39
                },
                "type": "PROPER"
            }
        ]
    },
    {
        "name": "stump",
        "type": "OTHER",
        "metadata": [],
        "salience": 0.11315115,
        "mentions": [
            {
                "text": {
                    "content": "stump",
                    "beginOffset": 30
                },
                "type": "COMMON"
            }
        ]
    },
    {
        "name": "fruit",
        "type": "OTHER",
        "metadata": [],
        "salience": 0.057235695,
        "mentions": [
            {
                "text": {
                    "content": "fruit",
                    "beginOffset": 80
                },
                "type": "COMMON"
            }
        ]
    },
    {
        "name": "Branch",
        "type": "ORGANIZATION",
        "metadata": [],
        "salience": 0.036275774,
        "mentions": [
            {
                "text": {
                    "content": "Branch",
                    "beginOffset": 63
                },
                "type": "COMMON"
            }
        ]
    },
    {
        "name": "roots",
        "type": "OTHER",
        "metadata": [],
        "salience": 0.036275774,
        "mentions": [
            {
                "text": {
                    "content": "roots",
                    "beginOffset": 55
                },
                "type": "COMMON"
            }
        ]
    }
]