[
    {
        "name": "Lord",
        "type": "PERSON",
        "metadata": [],
        "salience": 0.47887203,
        "mentions": [
            {
                "text": {
                    "content": "Lord",
                    "beginOffset": 33
                },
                "type": "COMMON"
            }
        ]
    },
    {
        "name": "counselor",
        "type": "PERSON",
        "metadata": [],
        "salience": 0.36172187,
        "mentions": [
            {
                "text": {
                    "content": "counselor",
                    "beginOffset": 59
                },
                "type": "COMMON"
            }
        ]
    },
    {
        "name": "mind",
        "type": "OTHER",
        "metadata": [],
        "salience": 0.15940608,
        "mentions": [
            {
                "text": {
                    "content": "mind",
                    "beginOffset": 21
                },
                "type": "COMMON"
            }
        ]
    }
]