[
    {
        "name": "man",
        "type": "PERSON",
        "metadata": [],
        "salience": 0.3876573,
        "mentions": [
            {
                "text": {
                    "content": "man",
                    "beginOffset": 294
                },
                "type": "COMMON"
            }
        ]
    },
    {
        "name": "people",
        "type": "PERSON",
        "metadata": [],
        "salience": 0.16362964,
        "mentions": [
            {
                "text": {
                    "content": "people",
                    "beginOffset": 49
                },
                "type": "COMMON"
            }
        ]
    },
    {
        "name": "someone",
        "type": "PERSON",
        "metadata": [],
        "salience": 0.15141906,
        "mentions": [
            {
                "text": {
                    "content": "someone",
                    "beginOffset": 376
                },
                "type": "COMMON"
            }
        ]
    },
    {
        "name": "God",
        "type": "PERSON",
        "metadata": {
            "mid": "\/m\/0d05l6",
            "wikipedia_url": "https:\/\/en.wikipedia.org\/wiki\/God"
        },
        "salience": 0.0633218,
        "mentions": [
            {
                "text": {
                    "content": "God",
                    "beginOffset": 3
                },
                "type": "PROPER"
            },
            {
                "text": {
                    "content": "God",
                    "beginOffset": 2033
                },
                "type": "PROPER"
            }
        ]
    },
    {
        "name": "children",
        "type": "PERSON",
        "metadata": [],
        "salience": 0.023735827,
        "mentions": [
            {
                "text": {
                    "content": "children",
                    "beginOffset": 596
                },
                "type": "COMMON"
            },
            {
                "text": {
                    "content": "children",
                    "beginOffset": 649
                },
                "type": "COMMON"
            }
        ]
    },
    {
        "name": "mouths",
        "type": "OTHER",
        "metadata": [],
        "salience": 0.022553548,
        "mentions": [
            {
                "text": {
                    "content": "mouths",
                    "beginOffset": 103
                },
                "type": "COMMON"
            }
        ]
    },
    {
        "name": "friendship",
        "type": "OTHER",
        "metadata": [],
        "salience": 0.020790482,
        "mentions": [
            {
                "text": {
                    "content": "friendship",
                    "beginOffset": 256
                },
                "type": "COMMON"
            },
            {
                "text": {
                    "content": "friendship",
                    "beginOffset": 356
                },
                "type": "COMMON"
            }
        ]
    },
    {
        "name": "accusers",
        "type": "PERSON",
        "metadata": [],
        "salience": 0.012998673,
        "mentions": [
            {
                "text": {
                    "content": "accusers",
                    "beginOffset": 1605
                },
                "type": "COMMON"
            },
            {
                "text": {
                    "content": "accusers",
                    "beginOffset": 1965
                },
                "type": "COMMON"
            },
            {
                "text": {
                    "content": "accusers",
                    "beginOffset": 2257
                },
                "type": "COMMON"
            }
        ]
    },
    {
        "name": "tongues",
        "type": "OTHER",
        "metadata": [],
        "salience": 0.0097883,
        "mentions": [
            {
                "text": {
                    "content": "tongues",
                    "beginOffset": 161
                },
                "type": "COMMON"
            }
        ]
    },
    {
        "name": "Lord",
        "type": "PERSON",
        "metadata": [],
        "salience": 0.009224377,
        "mentions": [
            {
                "text": {
                    "content": "Lord",
                    "beginOffset": 2126
                },
                "type": "COMMON"
            }
        ]
    },
    {
        "name": "descendants",
        "type": "PERSON",
        "metadata": [],
        "salience": 0.008136824,
        "mentions": [
            {
                "text": {
                    "content": "descendants",
                    "beginOffset": 887
                },
                "type": "COMMON"
            }
        ]
    },
    {
        "name": "Lord",
        "type": "PERSON",
        "metadata": [],
        "salience": 0.0062880106,
        "mentions": [
            {
                "text": {
                    "content": "Lord",
                    "beginOffset": 1018
                },
                "type": "COMMON"
            },
            {
                "text": {
                    "content": "Lord",
                    "beginOffset": 1112
                },
                "type": "COMMON"
            }
        ]
    },
    {
        "name": "hatred",
        "type": "OTHER",
        "metadata": [],
        "salience": 0.0053604627,
        "mentions": [
            {
                "text": {
                    "content": "hatred",
                    "beginOffset": 184
                },
                "type": "COMMON"
            }
        ]
    },
    {
        "name": "prayer",
        "type": "OTHER",
        "metadata": [],
        "salience": 0.005333862,
        "mentions": [
            {
                "text": {
                    "content": "prayer",
                    "beginOffset": 301
                },
                "type": "COMMON"
            }
        ]
    },
    {
        "name": "Lord",
        "type": "PERSON",
        "metadata": [],
        "salience": 0.0050557866,
        "mentions": [
            {
                "text": {
                    "content": "Lord",
                    "beginOffset": 2366
                },
                "type": "COMMON"
            }
        ]
    },
    {
        "name": "words",
        "type": "OTHER",
        "metadata": [],
        "salience": 0.0047099493,
        "mentions": [
            {
                "text": {
                    "content": "words",
                    "beginOffset": 175
                },
                "type": "COMMON"
            }
        ]
    },
    {
        "name": "cause",
        "type": "OTHER",
        "metadata": [],
        "salience": 0.0047099493,
        "mentions": [
            {
                "text": {
                    "content": "cause",
                    "beginOffset": 232
                },
                "type": "COMMON"
            }
        ]
    },
    {
        "name": "return",
        "type": "OTHER",
        "metadata": [],
        "salience": 0.0046865656,
        "mentions": [
            {
                "text": {
                    "content": "return",
                    "beginOffset": 242
                },
                "type": "COMMON"
            }
        ]
    },
    {
        "name": "curse",
        "type": "OTHER",
        "metadata": [],
        "salience": 0.003971549,
        "mentions": [
            {
                "text": {
                    "content": "curse",
                    "beginOffset": 1299
                },
                "type": "COMMON"
            }
        ]
    },
    {
        "name": "pleasure",
        "type": "OTHER",
        "metadata": [],
        "salience": 0.0034246526,
        "mentions": [
            {
                "text": {
                    "content": "pleasure",
                    "beginOffset": 1345
                },
                "type": "COMMON"
            }
        ]
    },
    {
        "name": "garment",
        "type": "CONSUMER_GOOD",
        "metadata": [],
        "salience": 0.0034222484,
        "mentions": [
            {
                "text": {
                    "content": "garment",
                    "beginOffset": 1416
                },
                "type": "COMMON"
            }
        ]
    },
    {
        "name": "hand",
        "type": "OTHER",
        "metadata": [],
        "salience": 0.0033234702,
        "mentions": [
            {
                "text": {
                    "content": "hand",
                    "beginOffset": 2110
                },
                "type": "COMMON"
            }
        ]
    },
    {
        "name": "kindness",
        "type": "OTHER",
        "metadata": [],
        "salience": 0.0024510052,
        "mentions": [
            {
                "text": {
                    "content": "kindness",
                    "beginOffset": 822
                },
                "type": "COMMON"
            }
        ]
    },
    {
        "name": "hand",
        "type": "OTHER",
        "metadata": [],
        "salience": 0.0022014687,
        "mentions": [
            {
                "text": {
                    "content": "hand",
                    "beginOffset": 443
                },
                "type": "COMMON"
            }
        ]
    },
    {
        "name": "hatred",
        "type": "OTHER",
        "metadata": [],
        "salience": 0.0020135057,
        "mentions": [
            {
                "text": {
                    "content": "hatred",
                    "beginOffset": 342
                },
                "type": "COMMON"
            }
        ]
    },
    {
        "name": "place",
        "type": "OTHER",
        "metadata": [],
        "salience": 0.0020109885,
        "mentions": [
            {
                "text": {
                    "content": "place",
                    "beginOffset": 567
                },
                "type": "COMMON"
            }
        ]
    },
    {
        "name": "prayers",
        "type": "OTHER",
        "metadata": [],
        "salience": 0.002003489,
        "mentions": [
            {
                "text": {
                    "content": "prayers",
                    "beginOffset": 504
                },
                "type": "COMMON"
            }
        ]
    },
    {
        "name": "Lord",
        "type": "PERSON",
        "metadata": [],
        "salience": 0.001940875,
        "mentions": [
            {
                "text": {
                    "content": "Lord",
                    "beginOffset": 1665
                },
                "type": "COMMON"
            }
        ]
    },
    {
        "name": "enemy",
        "type": "OTHER",
        "metadata": [],
        "salience": 0.0017637744,
        "mentions": [
            {
                "text": {
                    "content": "enemy",
                    "beginOffset": 402
                },
                "type": "COMMON"
            }
        ]
    },
    {
        "name": "accuser stand",
        "type": "OTHER",
        "metadata": [],
        "salience": 0.0017637744,
        "mentions": [
            {
                "text": {
                    "content": "accuser stand",
                    "beginOffset": 416
                },
                "type": "COMMON"
            }
        ]
    },
    {
        "name": "leadership",
        "type": "OTHER",
        "metadata": [],
        "salience": 0.0017564888,
        "mentions": [
            {
                "text": {
                    "content": "leadership",
                    "beginOffset": 576
                },
                "type": "COMMON"
            }
        ]
    },
    {
        "name": "few",
        "type": "OTHER",
        "metadata": [],
        "salience": 0.0017564888,
        "mentions": [
            {
                "text": {
                    "content": "few",
                    "beginOffset": 541
                },
                "type": "COMMON"
            }
        ]
    },
    {
        "name": "wife",
        "type": "PERSON",
        "metadata": [],
        "salience": 0.0017536058,
        "mentions": [
            {
                "text": {
                    "content": "wife",
                    "beginOffset": 627
                },
                "type": "COMMON"
            }
        ]
    },
    {
        "name": "widow",
        "type": "PERSON",
        "metadata": [],
        "salience": 0.0017536058,
        "mentions": [
            {
                "text": {
                    "content": "widow",
                    "beginOffset": 634
                },
                "type": "COMMON"
            }
        ]
    },
    {
        "name": "Lord",
        "type": "PERSON",
        "metadata": [],
        "salience": 0.0016927155,
        "mentions": [
            {
                "text": {
                    "content": "Lord",
                    "beginOffset": 1582
                },
                "type": "COMMON"
            }
        ]
    },
    {
        "name": "name",
        "type": "OTHER",
        "metadata": [],
        "salience": 0.0014845543,
        "mentions": [
            {
                "text": {
                    "content": "name",
                    "beginOffset": 1145
                },
                "type": "COMMON"
            }
        ]
    },
    {
        "name": "children",
        "type": "PERSON",
        "metadata": [],
        "salience": 0.0014707573,
        "mentions": [
            {
                "text": {
                    "content": "children",
                    "beginOffset": 869
                },
                "type": "COMMON"
            }
        ]
    },
    {
        "name": "sins",
        "type": "OTHER",
        "metadata": [],
        "salience": 0.0014660056,
        "mentions": [
            {
                "text": {
                    "content": "sins",
                    "beginOffset": 1082
                },
                "type": "COMMON"
            }
        ]
    },
    {
        "name": "kindness",
        "type": "OTHER",
        "metadata": [],
        "salience": 0.0013528679,
        "mentions": [
            {
                "text": {
                    "content": "kindness",
                    "beginOffset": 1198
                },
                "type": "COMMON"
            }
        ]
    },
    {
        "name": "poor",
        "type": "PERSON",
        "metadata": [],
        "salience": 0.0013528679,
        "mentions": [
            {
                "text": {
                    "content": "poor",
                    "beginOffset": 1233
                },
                "type": "COMMON"
            }
        ]
    },
    {
        "name": "needy",
        "type": "OTHER",
        "metadata": [],
        "salience": 0.0013528679,
        "mentions": [
            {
                "text": {
                    "content": "needy",
                    "beginOffset": 1246
                },
                "type": "COMMON"
            }
        ]
    },
    {
        "name": "pity",
        "type": "OTHER",
        "metadata": [],
        "salience": 0.001349012,
        "mentions": [
            {
                "text": {
                    "content": "pity",
                    "beginOffset": 846
                },
                "type": "COMMON"
            }
        ]
    },
    {
        "name": "payment",
        "type": "OTHER",
        "metadata": [],
        "salience": 0.001339124,
        "mentions": [
            {
                "text": {
                    "content": "payment",
                    "beginOffset": 1591
                },
                "type": "COMMON"
            }
        ]
    },
    {
        "name": "names",
        "type": "OTHER",
        "metadata": [],
        "salience": 0.0013314446,
        "mentions": [
            {
                "text": {
                    "content": "names",
                    "beginOffset": 917
                },
                "type": "COMMON"
            }
        ]
    },
    {
        "name": "Lord",
        "type": "PERSON",
        "metadata": [],
        "salience": 0.0012713758,
        "mentions": [
            {
                "text": {
                    "content": "Lord",
                    "beginOffset": 2025
                },
                "type": "COMMON"
            }
        ]
    },
    {
        "name": "body",
        "type": "OTHER",
        "metadata": [],
        "salience": 0.0012384236,
        "mentions": [
            {
                "text": {
                    "content": "body",
                    "beginOffset": 1445
                },
                "type": "COMMON"
            }
        ]
    },
    {
        "name": "cloak",
        "type": "OTHER",
        "metadata": [],
        "salience": 0.0012375999,
        "mentions": [
            {
                "text": {
                    "content": "cloak",
                    "beginOffset": 1504
                },
                "type": "COMMON"
            }
        ]
    },
    {
        "name": "mother",
        "type": "PERSON",
        "metadata": [],
        "salience": 0.0011903554,
        "mentions": [
            {
                "text": {
                    "content": "mother",
                    "beginOffset": 1043
                },
                "type": "COMMON"
            }
        ]
    },
    {
        "name": "earth",
        "type": "LOCATION",
        "metadata": [],
        "salience": 0.0011892702,
        "mentions": [
            {
                "text": {
                    "content": "earth",
                    "beginOffset": 1159
                },
                "type": "COMMON"
            }
        ]
    },
    {
        "name": "beggars",
        "type": "OTHER",
        "metadata": [],
        "salience": 0.0011811284,
        "mentions": [
            {
                "text": {
                    "content": "beggars",
                    "beginOffset": 671
                },
                "type": "COMMON"
            }
        ]
    },
    {
        "name": "homes",
        "type": "LOCATION",
        "metadata": [],
        "salience": 0.0011811284,
        "mentions": [
            {
                "text": {
                    "content": "homes",
                    "beginOffset": 717
                },
                "type": "COMMON"
            }
        ]
    },
    {
        "name": "strangers",
        "type": "PERSON",
        "metadata": [],
        "salience": 0.0011795979,
        "mentions": [
            {
                "text": {
                    "content": "strangers",
                    "beginOffset": 761
                },
                "type": "COMMON"
            }
        ]
    },
    {
        "name": "creditor",
        "type": "OTHER",
        "metadata": [],
        "salience": 0.0011795979,
        "mentions": [
            {
                "text": {
                    "content": "creditor",
                    "beginOffset": 730
                },
                "type": "COMMON"
            }
        ]
    },
    {
        "name": "fruits",
        "type": "OTHER",
        "metadata": [],
        "salience": 0.0011795979,
        "mentions": [
            {
                "text": {
                    "content": "fruits",
                    "beginOffset": 783
                },
                "type": "COMMON"
            }
        ]
    },
    {
        "name": "labor",
        "type": "OTHER",
        "metadata": [],
        "salience": 0.0011795979,
        "mentions": [
            {
                "text": {
                    "content": "labor",
                    "beginOffset": 797
                },
                "type": "COMMON"
            }
        ]
    },
    {
        "name": "generation",
        "type": "OTHER",
        "metadata": [],
        "salience": 0.001176954,
        "mentions": [
            {
                "text": {
                    "content": "generation",
                    "beginOffset": 949
                },
                "type": "COMMON"
            }
        ]
    },
    {
        "name": "fathers",
        "type": "PERSON",
        "metadata": [],
        "salience": 0.0011757951,
        "mentions": [
            {
                "text": {
                    "content": "fathers",
                    "beginOffset": 985
                },
                "type": "COMMON"
            }
        ]
    },
    {
        "name": "iniquity",
        "type": "OTHER",
        "metadata": [],
        "salience": 0.0011757951,
        "mentions": [
            {
                "text": {
                    "content": "iniquity",
                    "beginOffset": 969
                },
                "type": "COMMON"
            }
        ]
    },
    {
        "name": "blessing",
        "type": "OTHER",
        "metadata": [],
        "salience": 0.0010884956,
        "mentions": [
            {
                "text": {
                    "content": "blessing",
                    "beginOffset": 1357
                },
                "type": "COMMON"
            }
        ]
    },
    {
        "name": "bones",
        "type": "OTHER",
        "metadata": [],
        "salience": 0.00108773,
        "mentions": [
            {
                "text": {
                    "content": "bones",
                    "beginOffset": 1471
                },
                "type": "COMMON"
            }
        ]
    },
    {
        "name": "oil",
        "type": "OTHER",
        "metadata": [],
        "salience": 0.00108773,
        "mentions": [
            {
                "text": {
                    "content": "oil",
                    "beginOffset": 1482
                },
                "type": "COMMON"
            }
        ]
    },
    {
        "name": "water",
        "type": "OTHER",
        "metadata": [],
        "salience": 0.00108773,
        "mentions": [
            {
                "text": {
                    "content": "water",
                    "beginOffset": 1455
                },
                "type": "COMMON"
            }
        ]
    },
    {
        "name": "belt",
        "type": "OTHER",
        "metadata": [],
        "salience": 0.0010870064,
        "mentions": [
            {
                "text": {
                    "content": "belt",
                    "beginOffset": 1536
                },
                "type": "COMMON"
            }
        ]
    },
    {
        "name": "evil",
        "type": "OTHER",
        "metadata": [],
        "salience": 0.0010863204,
        "mentions": [
            {
                "text": {
                    "content": "evil",
                    "beginOffset": 1634
                },
                "type": "COMMON"
            }
        ]
    },
    {
        "name": "sin",
        "type": "OTHER",
        "metadata": [],
        "salience": 0.0010787362,
        "mentions": [
            {
                "text": {
                    "content": "sin",
                    "beginOffset": 1032
                },
                "type": "COMMON"
            }
        ]
    },
    {
        "name": "love",
        "type": "OTHER",
        "metadata": [],
        "salience": 0.0009288796,
        "mentions": [
            {
                "text": {
                    "content": "love",
                    "beginOffset": 2074
                },
                "type": "COMMON"
            }
        ]
    },
    {
        "name": "heads",
        "type": "OTHER",
        "metadata": [],
        "salience": 0.000816223,
        "mentions": [
            {
                "text": {
                    "content": "heads",
                    "beginOffset": 2010
                },
                "type": "COMMON"
            }
        ]
    },
    {
        "name": "scorn",
        "type": "OTHER",
        "metadata": [],
        "salience": 0.000816223,
        "mentions": [
            {
                "text": {
                    "content": "scorn",
                    "beginOffset": 1953
                },
                "type": "COMMON"
            }
        ]
    },
    {
        "name": "object",
        "type": "OTHER",
        "metadata": [],
        "salience": 0.000816223,
        "mentions": [
            {
                "text": {
                    "content": "object",
                    "beginOffset": 1943
                },
                "type": "COMMON"
            }
        ]
    },
    {
        "name": "hand",
        "type": "OTHER",
        "metadata": [],
        "salience": 0.00071115175,
        "mentions": [
            {
                "text": {
                    "content": "hand",
                    "beginOffset": 2452
                },
                "type": "COMMON"
            }
        ]
    },
    {
        "name": "shame",
        "type": "OTHER",
        "metadata": [],
        "salience": 0.0006494004,
        "mentions": [
            {
                "text": {
                    "content": "shame",
                    "beginOffset": 2213
                },
                "type": "COMMON"
            }
        ]
    },
    {
        "name": "cloak",
        "type": "OTHER",
        "metadata": [],
        "salience": 0.0006491199,
        "mentions": [
            {
                "text": {
                    "content": "cloak",
                    "beginOffset": 2320
                },
                "type": "COMMON"
            }
        ]
    },
    {
        "name": "shame",
        "type": "OTHER",
        "metadata": [],
        "salience": 0.0006491199,
        "mentions": [
            {
                "text": {
                    "content": "shame",
                    "beginOffset": 2306
                },
                "type": "COMMON"
            }
        ]
    },
    {
        "name": "mouth",
        "type": "OTHER",
        "metadata": [],
        "salience": 0.00064884906,
        "mentions": [
            {
                "text": {
                    "content": "mouth",
                    "beginOffset": 2335
                },
                "type": "COMMON"
            }
        ]
    },
    {
        "name": "needy",
        "type": "OTHER",
        "metadata": [],
        "salience": 0.0006485871,
        "mentions": [
            {
                "text": {
                    "content": "needy",
                    "beginOffset": 2464
                },
                "type": "COMMON"
            }
        ]
    },
    {
        "name": "knees",
        "type": "OTHER",
        "metadata": [],
        "salience": 0.00059293583,
        "mentions": [
            {
                "text": {
                    "content": "knees",
                    "beginOffset": 1879
                },
                "type": "COMMON"
            }
        ]
    },
    {
        "name": "servant",
        "type": "PERSON",
        "metadata": [],
        "salience": 0.0005703498,
        "mentions": [
            {
                "text": {
                    "content": "servant",
                    "beginOffset": 2233
                },
                "type": "COMMON"
            }
        ]
    },
    {
        "name": "disgrace",
        "type": "OTHER",
        "metadata": [],
        "salience": 0.0005701034,
        "mentions": [
            {
                "text": {
                    "content": "disgrace",
                    "beginOffset": 2282
                },
                "type": "COMMON"
            }
        ]
    },
    {
        "name": "throng",
        "type": "OTHER",
        "metadata": [],
        "salience": 0.0005698655,
        "mentions": [
            {
                "text": {
                    "content": "throng",
                    "beginOffset": 2385
                },
                "type": "COMMON"
            }
        ]
    },
    {
        "name": "worshipers",
        "type": "PERSON",
        "metadata": [],
        "salience": 0.0005698655,
        "mentions": [
            {
                "text": {
                    "content": "worshipers",
                    "beginOffset": 2395
                },
                "type": "COMMON"
            }
        ]
    },
    {
        "name": "lives",
        "type": "OTHER",
        "metadata": [],
        "salience": 0.0005696355,
        "mentions": [
            {
                "text": {
                    "content": "lives",
                    "beginOffset": 2485
                },
                "type": "COMMON"
            }
        ]
    },
    {
        "name": "body",
        "type": "OTHER",
        "metadata": [],
        "salience": 0.0004901692,
        "mentions": [
            {
                "text": {
                    "content": "body",
                    "beginOffset": 1911
                },
                "type": "COMMON"
            }
        ]
    },
    {
        "name": "name",
        "type": "OTHER",
        "metadata": [],
        "salience": 0.00044755163,
        "mentions": [
            {
                "text": {
                    "content": "name",
                    "beginOffset": 1688
                },
                "type": "COMMON"
            }
        ]
    },
    {
        "name": "love",
        "type": "OTHER",
        "metadata": [],
        "salience": 0.00040817057,
        "mentions": [
            {
                "text": {
                    "content": "love",
                    "beginOffset": 1731
                },
                "type": "COMMON"
            }
        ]
    },
    {
        "name": "sake",
        "type": "OTHER",
        "metadata": [],
        "salience": 0.0003584767,
        "mentions": [
            {
                "text": {
                    "content": "sake",
                    "beginOffset": 1697
                },
                "type": "COMMON"
            }
        ]
    },
    {
        "name": "goodness",
        "type": "OTHER",
        "metadata": [],
        "salience": 0.0003584767,
        "mentions": [
            {
                "text": {
                    "content": "goodness",
                    "beginOffset": 1714
                },
                "type": "COMMON"
            }
        ]
    },
    {
        "name": "heart",
        "type": "OTHER",
        "metadata": [],
        "salience": 0.00035827138,
        "mentions": [
            {
                "text": {
                    "content": "heart",
                    "beginOffset": 1781
                },
                "type": "COMMON"
            }
        ]
    },
    {
        "name": "locust",
        "type": "OTHER",
        "metadata": [],
        "salience": 0.00035807534,
        "mentions": [
            {
                "text": {
                    "content": "locust",
                    "beginOffset": 1868
                },
                "type": "COMMON"
            }
        ]
    },
    {
        "name": "evening shadow",
        "type": "CONSUMER_GOOD",
        "metadata": [],
        "salience": 0.00035807534,
        "mentions": [
            {
                "text": {
                    "content": "evening shadow",
                    "beginOffset": 1829
                },
                "type": "COMMON"
            }
        ]
    },
    {
        "name": "fasting",
        "type": "OTHER",
        "metadata": [],
        "salience": 0.0003578877,
        "mentions": [
            {
                "text": {
                    "content": "fasting",
                    "beginOffset": 1899
                },
                "type": "COMMON"
            }
        ]
    },
    {
        "name": "way",
        "type": "OTHER",
        "metadata": [],
        "salience": 0.00027294885,
        "mentions": [
            {
                "text": {
                    "content": "way",
                    "beginOffset": 1890
                },
                "type": "COMMON"
            }
        ]
    },
    {
        "name": "Sovereign",
        "type": "ORGANIZATION",
        "metadata": [],
        "salience": 0.00021177767,
        "mentions": [
            {
                "text": {
                    "content": "Sovereign",
                    "beginOffset": 1655
                },
                "type": "PROPER"
            }
        ]
    }
]