[
    {
        "name": "temple",
        "type": "OTHER",
        "metadata": [],
        "salience": 0.5513071,
        "mentions": [
            {
                "text": {
                    "content": "temple",
                    "beginOffset": 80
                },
                "type": "COMMON"
            }
        ]
    },
    {
        "name": "Lord",
        "type": "PERSON",
        "metadata": [],
        "salience": 0.08009867,
        "mentions": [
            {
                "text": {
                    "content": "Lord",
                    "beginOffset": 94
                },
                "type": "COMMON"
            }
        ]
    },
    {
        "name": "altar",
        "type": "OTHER",
        "metadata": [],
        "salience": 0.08009867,
        "mentions": [
            {
                "text": {
                    "content": "altar",
                    "beginOffset": 104
                },
                "type": "COMMON"
            }
        ]
    },
    {
        "name": "burnt offering",
        "type": "OTHER",
        "metadata": [],
        "salience": 0.07369781,
        "mentions": [
            {
                "text": {
                    "content": "burnt offering",
                    "beginOffset": 113
                },
                "type": "COMMON"
            }
        ]
    },
    {
        "name": "King Hezekiah",
        "type": "PERSON",
        "metadata": {
            "mid": "\/m\/03myb",
            "wikipedia_url": "https:\/\/en.wikipedia.org\/wiki\/Hezekiah"
        },
        "salience": 0.0696498,
        "mentions": [
            {
                "text": {
                    "content": "King Hezekiah",
                    "beginOffset": 21
                },
                "type": "PROPER"
            }
        ]
    },
    {
        "name": "bread",
        "type": "OTHER",
        "metadata": [],
        "salience": 0.055966727,
        "mentions": [
            {
                "text": {
                    "content": "bread",
                    "beginOffset": 197
                },
                "type": "COMMON"
            }
        ]
    },
    {
        "name": "articles",
        "type": "WORK_OF_ART",
        "metadata": [],
        "salience": 0.039449446,
        "mentions": [
            {
                "text": {
                    "content": "articles",
                    "beginOffset": 217
                },
                "type": "COMMON"
            }
        ]
    },
    {
        "name": "utensils",
        "type": "OTHER",
        "metadata": [],
        "salience": 0.024865892,
        "mentions": [
            {
                "text": {
                    "content": "utensils",
                    "beginOffset": 141
                },
                "type": "COMMON"
            }
        ]
    },
    {
        "name": "table",
        "type": "OTHER",
        "metadata": [],
        "salience": 0.024865892,
        "mentions": [
            {
                "text": {
                    "content": "table",
                    "beginOffset": 159
                },
                "type": "COMMON"
            }
        ]
    }
]