[
    {
        "name": "Bethuel",
        "type": "PERSON",
        "metadata": {
            "wikipedia_url": "https:\/\/en.wikipedia.org\/wiki\/Bethuel",
            "mid": "\/m\/08vm1n"
        },
        "salience": 0.7063267,
        "mentions": [
            {
                "text": {
                    "content": "Bethuel",
                    "beginOffset": 0
                },
                "type": "PROPER"
            }
        ]
    },
    {
        "name": "Hormah",
        "type": "LOCATION",
        "metadata": {
            "mid": "\/m\/06j23g",
            "wikipedia_url": "https:\/\/en.wikipedia.org\/wiki\/Hormah"
        },
        "salience": 0.22174805,
        "mentions": [
            {
                "text": {
                    "content": "Hormah",
                    "beginOffset": 9
                },
                "type": "PROPER"
            }
        ]
    },
    {
        "name": "Ziklag",
        "type": "LOCATION",
        "metadata": {
            "mid": "\/m\/0hz9k",
            "wikipedia_url": "https:\/\/en.wikipedia.org\/wiki\/Ziklag"
        },
        "salience": 0.07192525,
        "mentions": [
            {
                "text": {
                    "content": "Ziklag",
                    "beginOffset": 17
                },
                "type": "PROPER"
            }
        ]
    }
]