[
    {
        "name": "lion",
        "type": "OTHER",
        "metadata": [],
        "salience": 0.23674315,
        "mentions": [
            {
                "text": {
                    "content": "lion",
                    "beginOffset": 12
                },
                "type": "COMMON"
            }
        ]
    },
    {
        "name": "forest",
        "type": "LOCATION",
        "metadata": [],
        "salience": 0.23674315,
        "mentions": [
            {
                "text": {
                    "content": "forest",
                    "beginOffset": 26
                },
                "type": "COMMON"
            }
        ]
    },
    {
        "name": "wolf",
        "type": "OTHER",
        "metadata": [],
        "salience": 0.09524612,
        "mentions": [
            {
                "text": {
                    "content": "wolf",
                    "beginOffset": 53
                },
                "type": "COMMON"
            }
        ]
    },
    {
        "name": "many",
        "type": "PERSON",
        "metadata": [],
        "salience": 0.080844715,
        "mentions": [
            {
                "text": {
                    "content": "many",
                    "beginOffset": 227
                },
                "type": "COMMON"
            }
        ]
    },
    {
        "name": "leopard",
        "type": "OTHER",
        "metadata": [],
        "salience": 0.06583432,
        "mentions": [
            {
                "text": {
                    "content": "leopard",
                    "beginOffset": 94
                },
                "type": "COMMON"
            }
        ]
    },
    {
        "name": "desert",
        "type": "LOCATION",
        "metadata": [],
        "salience": 0.06504995,
        "mentions": [
            {
                "text": {
                    "content": "desert",
                    "beginOffset": 67
                },
                "type": "COMMON"
            }
        ]
    },
    {
        "name": "wait",
        "type": "LOCATION",
        "metadata": [],
        "salience": 0.06053118,
        "mentions": [
            {
                "text": {
                    "content": "wait",
                    "beginOffset": 114
                },
                "type": "COMMON"
            }
        ]
    },
    {
        "name": "towns",
        "type": "LOCATION",
        "metadata": [],
        "salience": 0.06053118,
        "mentions": [
            {
                "text": {
                    "content": "towns",
                    "beginOffset": 130
                },
                "type": "COMMON"
            }
        ]
    },
    {
        "name": "rebellion",
        "type": "EVENT",
        "metadata": [],
        "salience": 0.04587941,
        "mentions": [
            {
                "text": {
                    "content": "rebellion",
                    "beginOffset": 185
                },
                "type": "COMMON"
            }
        ]
    },
    {
        "name": "backslidings",
        "type": "OTHER",
        "metadata": [],
        "salience": 0.032281287,
        "mentions": [
            {
                "text": {
                    "content": "backslidings",
                    "beginOffset": 214
                },
                "type": "COMMON"
            }
        ]
    },
    {
        "name": "pieces",
        "type": "OTHER",
        "metadata": [],
        "salience": 0.020315532,
        "mentions": [
            {
                "text": {
                    "content": "pieces",
                    "beginOffset": 147
                },
                "type": "COMMON"
            }
        ]
    }
]