[
    {
        "name": "place",
        "type": "LOCATION",
        "metadata": [],
        "salience": 0.8484152,
        "mentions": [
            {
                "text": {
                    "content": "place",
                    "beginOffset": 19
                },
                "type": "COMMON"
            }
        ]
    },
    {
        "name": "land",
        "type": "LOCATION",
        "metadata": [],
        "salience": 0.15158479,
        "mentions": [
            {
                "text": {
                    "content": "land",
                    "beginOffset": 79
                },
                "type": "COMMON"
            }
        ]
    }
]