[
    {
        "name": "passing breeze",
        "type": "OTHER",
        "metadata": [],
        "salience": 0.7154555,
        "mentions": [
            {
                "text": {
                    "content": "passing breeze",
                    "beginOffset": 42
                },
                "type": "COMMON"
            }
        ]
    },
    {
        "name": "flesh",
        "type": "OTHER",
        "metadata": [],
        "salience": 0.28454453,
        "mentions": [
            {
                "text": {
                    "content": "flesh",
                    "beginOffset": 33
                },
                "type": "COMMON"
            }
        ]
    }
]