[
    {
        "name": "God",
        "type": "PERSON",
        "metadata": {
            "mid": "\/m\/0d05l6",
            "wikipedia_url": "https:\/\/en.wikipedia.org\/wiki\/God"
        },
        "salience": 0.9670883,
        "mentions": [
            {
                "text": {
                    "content": "God",
                    "beginOffset": 0
                },
                "type": "PROPER"
            },
            {
                "text": {
                    "content": "judge",
                    "beginOffset": 19
                },
                "type": "COMMON"
            },
            {
                "text": {
                    "content": "God",
                    "beginOffset": 28
                },
                "type": "PROPER"
            }
        ]
    },
    {
        "name": "wrath",
        "type": "OTHER",
        "metadata": [],
        "salience": 0.032911688,
        "mentions": [
            {
                "text": {
                    "content": "wrath",
                    "beginOffset": 49
                },
                "type": "COMMON"
            }
        ]
    }
]