[
    {
        "name": "No one",
        "type": "PERSON",
        "metadata": [],
        "salience": 0.37521368,
        "mentions": [
            {
                "text": {
                    "content": "No one",
                    "beginOffset": 3
                },
                "type": "COMMON"
            }
        ]
    },
    {
        "name": "patch",
        "type": "OTHER",
        "metadata": [],
        "salience": 0.1650233,
        "mentions": [
            {
                "text": {
                    "content": "patch",
                    "beginOffset": 17
                },
                "type": "COMMON"
            }
        ]
    },
    {
        "name": "garment",
        "type": "CONSUMER_GOOD",
        "metadata": [],
        "salience": 0.11643468,
        "mentions": [
            {
                "text": {
                    "content": "garment",
                    "beginOffset": 51
                },
                "type": "COMMON"
            }
        ]
    },
    {
        "name": "patch",
        "type": "OTHER",
        "metadata": [],
        "salience": 0.10745816,
        "mentions": [
            {
                "text": {
                    "content": "patch",
                    "beginOffset": 68
                },
                "type": "COMMON"
            }
        ]
    },
    {
        "name": "cloth",
        "type": "OTHER",
        "metadata": [],
        "salience": 0.10198168,
        "mentions": [
            {
                "text": {
                    "content": "cloth",
                    "beginOffset": 35
                },
                "type": "COMMON"
            }
        ]
    },
    {
        "name": "garment",
        "type": "CONSUMER_GOOD",
        "metadata": [],
        "salience": 0.08230272,
        "mentions": [
            {
                "text": {
                    "content": "garment",
                    "beginOffset": 98
                },
                "type": "COMMON"
            }
        ]
    },
    {
        "name": "tear",
        "type": "OTHER",
        "metadata": [],
        "salience": 0.0515858,
        "mentions": [
            {
                "text": {
                    "content": "tear",
                    "beginOffset": 118
                },
                "type": "COMMON"
            }
        ]
    }
]