[
    {
        "name": "disciples",
        "type": "PERSON",
        "metadata": [],
        "salience": 0.89709944,
        "mentions": [
            {
                "text": {
                    "content": "disciples",
                    "beginOffset": 4
                },
                "type": "COMMON"
            }
        ]
    },
    {
        "name": "Jesus",
        "type": "PERSON",
        "metadata": {
            "mid": "\/m\/045m1_",
            "wikipedia_url": "https:\/\/en.wikipedia.org\/wiki\/Jesus"
        },
        "salience": 0.10290054,
        "mentions": [
            {
                "text": {
                    "content": "Jesus",
                    "beginOffset": 30
                },
                "type": "PROPER"
            }
        ]
    }
]